README.md
setup.py
basepackage/__init__.py
basepackage/base.py
giomikelbasepackage.egg-info/PKG-INFO
giomikelbasepackage.egg-info/SOURCES.txt
giomikelbasepackage.egg-info/dependency_links.txt
giomikelbasepackage.egg-info/top_level.txt