Metadata-Version: 2.1
Name: giomikelbasepackage
Version: 0.1
Summary: A Python package
Home-page: UNKNOWN
Author: Giorgi Mikeladze
Author-email: giorgi.mikeladze.4@iliauni.edu.ge
License: UNKNOWN
Platform: UNKNOWN
